alpha_vantage_client/__init__.py
alpha_vantage_client/cli.py
alpha_vantage_client/client.py
alpha_vantage_client-0.1.1.dist-info/licenses/LICENSE
alpha_vantage_client-0.1.1.dist-info/METADATA
alpha_vantage_client-0.1.1.dist-info/WHEEL
alpha_vantage_client-0.1.1.dist-info/entry_points.txt
alpha_vantage_client-0.1.1.dist-info/top_level.txt
alpha_vantage_client-0.1.1.dist-info/RECORD
