Metadata-Version: 2.4
Name: alpha-vantage-client
Version: 0.1.1
Summary: A comprehensive Python client for Alpha Vantage API with configuration-driven endpoints
Author-email: Judah Boyce <judahworkflow@gmail.com>
Maintainer-email: Judah Boyce <judahworkflow@gmail.com>
License-Expression: MIT
Project-URL: Homepage, https://github.com/Judah-fuego/alpha_vantage
Project-URL: Repository, https://github.com/Judah-fuego/alpha_vantage
Project-URL: Bug Tracker, https://github.com/Judah-fuego/alpha-vantage-client/issues
Project-URL: Source Code, https://github.com/Judah-fuego/alpha-vantage-client
Keywords: alpha-vantage,finance,stocks,crypto,forex,api,trading,market-data
Classifier: Development Status :: 4 - Beta
Classifier: Intended Audience :: Developers
Classifier: Intended Audience :: Financial and Insurance Industry
Classifier: Operating System :: OS Independent
Classifier: Programming Language :: Python :: 3
Classifier: Programming Language :: Python :: 3.8
Classifier: Programming Language :: Python :: 3.9
Classifier: Programming Language :: Python :: 3.10
Classifier: Programming Language :: Python :: 3.11
Classifier: Programming Language :: Python :: 3.12
Classifier: Topic :: Office/Business :: Financial
Classifier: Topic :: Office/Business :: Financial :: Investment
Classifier: Topic :: Software Development :: Libraries :: Python Modules
Classifier: Topic :: Internet :: WWW/HTTP :: Dynamic Content
Classifier: Topic :: Scientific/Engineering :: Information Analysis
Requires-Python: >=3.8
License-File: LICENSE
Requires-Dist: requests>=2.25.0
Requires-Dist: python-dateutil>=2.8.0
Provides-Extra: dev
Requires-Dist: pytest>=6.0; extra == "dev"
Requires-Dist: pytest-cov>=2.0; extra == "dev"
Requires-Dist: black>=21.0; extra == "dev"
Requires-Dist: flake8>=3.8; extra == "dev"
Requires-Dist: mypy>=0.800; extra == "dev"
Requires-Dist: python-dotenv>=0.19.0; extra == "dev"
Provides-Extra: docs
Requires-Dist: sphinx>=4.0; extra == "docs"
Requires-Dist: sphinx-rtd-theme>=1.0; extra == "docs"
Dynamic: license-file
